compas_fea/__init__.py
compas_fea/cad/__init__.py
compas_fea/cad/blender.py
compas_fea/cad/rhino.py
compas_fea/fea/__init__.py
compas_fea/fea/bcs.py
compas_fea/fea/constraints.py
compas_fea/fea/elements.py
compas_fea/fea/heading.py
compas_fea/fea/materials.py
compas_fea/fea/misc.py
compas_fea/fea/nodes.py
compas_fea/fea/sets.py
compas_fea/fea/steps.py
compas_fea/fea/writer.py
compas_fea/fea/abaq/__init__.py
compas_fea/fea/abaq/abaq.py
compas_fea/fea/abaq/launch_job.py
compas_fea/fea/abaq/odb_extract.py
compas_fea/fea/ansys/__init__.py
compas_fea/fea/ansys/ansys.py
compas_fea/fea/ansys/ansys_file_writer.py
compas_fea/fea/ansys/reading/__init__.py
compas_fea/fea/ansys/reading/ansys_read.py
compas_fea/fea/ansys/utilities/__init__.py
compas_fea/fea/ansys/utilities/modal_assurance_criterion.py
compas_fea/fea/ansys/utilities/remesh.py
compas_fea/fea/ansys/writing/__init__.py
compas_fea/fea/ansys/writing/ansys_acoustic.py
compas_fea/fea/ansys/writing/ansys_forces.py
compas_fea/fea/ansys/writing/ansys_harmonic.py
compas_fea/fea/ansys/writing/ansys_loads.py
compas_fea/fea/ansys/writing/ansys_materials.py
compas_fea/fea/ansys/writing/ansys_modal.py
compas_fea/fea/ansys/writing/ansys_nodes_elements.py
compas_fea/fea/ansys/writing/ansys_process.py
compas_fea/fea/ansys/writing/ansys_static.py
compas_fea/fea/ansys/writing/ansys_steps.py
compas_fea/fea/ansys/writing/ansys_stresses.py
compas_fea/fea/opensees/__init__.py
compas_fea/fea/opensees/opensees.py
compas_fea/structure/__init__.py
compas_fea/structure/constraint.py
compas_fea/structure/displacement.py
compas_fea/structure/element.py
compas_fea/structure/element_properties.py
compas_fea/structure/interaction.py
compas_fea/structure/load.py
compas_fea/structure/material.py
compas_fea/structure/misc.py
compas_fea/structure/node.py
compas_fea/structure/section.py
compas_fea/structure/set.py
compas_fea/structure/step.py
compas_fea/structure/structure.py
compas_fea/structure/mixins/__init__.py
compas_fea-0.3.3.dist-info/AUTHORS.md
compas_fea-0.3.3.dist-info/LICENSE
compas_fea-0.3.3.dist-info/METADATA
compas_fea-0.3.3.dist-info/WHEEL
compas_fea-0.3.3.dist-info/entry_points.txt
compas_fea-0.3.3.dist-info/top_level.txt
compas_fea-0.3.3.dist-info/RECORD
