Metadata-Version: 2.1
Name: compas-fea
Version: 0.3.3
Summary: compas finite element package
Home-page: https://github.com/compas-dev/compas_fea
Author: Andrew Liew
Author-email: a.liew@sheffield.ac.uk
License: MIT license
Platform: UNKNOWN
Classifier: Development Status :: 4 - Beta
Classifier: Intended Audience :: Developers
Classifier: Topic :: Scientific/Engineering
Classifier: License :: OSI Approved :: MIT License
Classifier: Operating System :: Unix
Classifier: Operating System :: POSIX
Classifier: Operating System :: Microsoft :: Windows
Classifier: Programming Language :: Python
Classifier: Programming Language :: Python :: 2.7
Classifier: Programming Language :: Python :: 3
Classifier: Programming Language :: Python :: 3.4
Classifier: Programming Language :: Python :: 3.5
Classifier: Programming Language :: Python :: 3.6
Classifier: Programming Language :: Python :: 3.7
Classifier: Programming Language :: Python :: Implementation :: CPython
Requires-Python: >=2.7
License-File: LICENSE
License-File: AUTHORS.md
Requires-Dist: COMPAS (>=1.0)
